rgain3/__init__.py
rgain3/albumid.py
rgain3/rgcalc.py
rgain3/rgio.py
rgain3/util.py
rgain3/version.py
rgain3/script/__init__.py
rgain3/script/collectiongain.py
rgain3/script/replaygain.py
rgain3-1.1.1.data/scripts/collectiongain
rgain3-1.1.1.data/scripts/replaygain
rgain3-1.1.1.dist-info/COPYING
rgain3-1.1.1.dist-info/METADATA
rgain3-1.1.1.dist-info/WHEEL
rgain3-1.1.1.dist-info/top_level.txt
rgain3-1.1.1.dist-info/RECORD
